pystrgpw.py
pystrgpw-1.0.1.dist-info/LICENSE
pystrgpw-1.0.1.dist-info/METADATA
pystrgpw-1.0.1.dist-info/WHEEL
pystrgpw-1.0.1.dist-info/top_level.txt
pystrgpw-1.0.1.dist-info/RECORD
