Metadata-Version: 2.1
Name: pystrgpw
Version: 1.0.1
Summary: A simple package that generates random characters and can be used for strong passwords.
Home-page: https://github.com/LordDashMe/pystrgpw
Author: Joshua Clifford Reyes
Author-email: reyesjoshuaclifford@gmail.com
Classifier: Programming Language :: Python :: 3.9
Classifier: Programming Language :: Python :: 3.10
Classifier: License :: OSI Approved :: MIT License
Classifier: Operating System :: OS Independent
License-File: LICENSE
Provides-Extra: dev
Requires-Dist: pytest ; extra == 'dev'
